{"name": "0039.png", "type": "110", "params": {"spots": [{"radius": 25, "center": [1487, 1938], "rad_w": 11, "rad_h": 11, "sigma": 50.0}, {"radius": 59, "center": [491, 802], "rad_w": 25, "rad_h": 21, "sigma": 104.39999999999999}, {"radius": 69, "center": [637, 840], "rad_w": 25, "rad_h": 29, "sigma": 120.39999999999999}, {"radius": 26, "center": [1077, 360], "rad_w": 11, "rad_h": 11, "sigma": 51.6}, {"radius": 37, "center": [930, 1281], "rad_w": 17, "rad_h": 17, "sigma": 69.2}], "blur": {"sigma": 10.587515911149001, "rad_w": 5, "rad_h": 5}}}