{"name": "0071.png", "type": "111", "params": {"illumination": {"color": {"brightness_factor": 0.8871703246704598, "contrast_factor": 0.9058812158908504, "saturation_factor": 0.6578266147776}, "halo": {"num": 1, "center_a": [1520, 1510], "dia_a": 3002.035246114397, "center_b": [1520, 1510], "dia_b": 5714.668514316041}, "hole": {"center": [1818, 1497], "diameter_circle": 2106, "brightness_factor": -0.291250629563998, "rad_w": 1457, "rad_h": 1191, "sigma": 1164.8}}, "spots": [{"radius": 47, "center": [2071, 131], "rad_w": 21, "rad_h": 17, "sigma": 85.19999999999999}, {"radius": 55, "center": [1134, 1161], "rad_w": 23, "rad_h": 21, "sigma": 98.0}, {"radius": 52, "center": [2209, 1597], "rad_w": 19, "rad_h": 21, "sigma": 93.2}, {"radius": 104, "center": [2417, 1222], "rad_w": 43, "rad_h": 35, "sigma": 176.4}, {"radius": 56, "center": [2670, 258], "rad_w": 23, "rad_h": 21, "sigma": 99.60000000000001}, {"radius": 37, "center": [200, 2831], "rad_w": 15, "rad_h": 15, "sigma": 69.2}], "blur": {"sigma": 14.81115009841995, "rad_w": 5, "rad_h": 7}}}