{"name": "0161.png", "type": "011", "params": {"illumination": {"color": {"brightness_factor": 0.777435494409483, "contrast_factor": 0.7190908296816815, "saturation_factor": 0.86715260876939}, "halo": {"num": 2, "center_a": [1311, 1849], "dia_a": 2674.2548449268647, "center_b": [1311, 1849], "dia_b": 5158.540958800578}, "hole": {"center": [1735, 1966], "diameter_circle": 2176, "brightness_factor": -0.28593825142214246, "rad_w": 1225, "rad_h": 1457, "sigma": 1165.6}}, "spots": [{"radius": 103, "center": [2648, 2548], "rad_w": 35, "rad_h": 35, "sigma": 174.8}, {"radius": 58, "center": [328, 2605], "rad_w": 23, "rad_h": 23, "sigma": 102.8}, {"radius": 38, "center": [2794, 471], "rad_w": 17, "rad_h": 17, "sigma": 70.8}, {"radius": 56, "center": [253, 2682], "rad_w": 25, "rad_h": 25, "sigma": 99.60000000000001}, {"radius": 157, "center": [2028, 1591], "rad_w": 61, "rad_h": 53, "sigma": 261.20000000000005}, {"radius": 41, "center": [2599, 1118], "rad_w": 17, "rad_h": 17, "sigma": 75.6}, {"radius": 127, "center": [607, 1196], "rad_w": 47, "rad_h": 45, "sigma": 213.2}, {"radius": 149, "center": [1015, 1092], "rad_w": 53, "rad_h": 51, "sigma": 248.4}]}}