{"name": "0220.png", "type": "010", "params": {"spots": [{"radius": 40, "center": [2647, 397], "rad_w": 17, "rad_h": 19, "sigma": 74.0}, {"radius": 114, "center": [371, 2665], "rad_w": 49, "rad_h": 43, "sigma": 192.39999999999998}, {"radius": 126, "center": [1355, 2556], "rad_w": 53, "rad_h": 47, "sigma": 211.6}, {"radius": 128, "center": [335, 1521], "rad_w": 45, "rad_h": 47, "sigma": 214.8}, {"radius": 130, "center": [2386, 1804], "rad_w": 45, "rad_h": 53, "sigma": 218.0}, {"radius": 118, "center": [590, 1690], "rad_w": 43, "rad_h": 45, "sigma": 198.79999999999998}, {"radius": 28, "center": [1260, 1307], "rad_w": 13, "rad_h": 13, "sigma": 54.800000000000004}, {"radius": 131, "center": [2425, 1970], "rad_w": 43, "rad_h": 45, "sigma": 219.60000000000002}]}}