{"name": "0383.png", "type": "011", "params": {"illumination": {"color": {"brightness_factor": 0.8550394239027523, "contrast_factor": 0.9021780589734627, "saturation_factor": 0.8744145523403528}, "halo": {"num": 2, "center_a": [1722, 1280], "dia_a": 2748.3345256584053, "center_b": [1722, 1280], "dia_b": 6550.557566965859}, "hole": {"center": [903, 1646], "diameter_circle": 1718, "brightness_factor": -0.284306209874153, "rad_w": 1253, "rad_h": 1041, "sigma": 1002.3999999999999}}, "spots": [{"radius": 91, "center": [2474, 219], "rad_w": 37, "rad_h": 31, "sigma": 155.6}, {"radius": 79, "center": [1324, 2029], "rad_w": 27, "rad_h": 27, "sigma": 136.4}, {"radius": 74, "center": [2128, 1540], "rad_w": 27, "rad_h": 29, "sigma": 128.4}, {"radius": 63, "center": [2864, 729], "rad_w": 23, "rad_h": 23, "sigma": 110.8}, {"radius": 142, "center": [2793, 2576], "rad_w": 51, "rad_h": 49, "sigma": 237.2}, {"radius": 103, "center": [826, 195], "rad_w": 39, "rad_h": 35, "sigma": 174.8}, {"radius": 135, "center": [2503, 182], "rad_w": 55, "rad_h": 53, "sigma": 226.0}, {"radius": 74, "center": [1879, 406], "rad_w": 33, "rad_h": 29, "sigma": 128.4}, {"radius": 88, "center": [144, 268], "rad_w": 31, "rad_h": 33, "sigma": 150.8}]}}