{"name": "0421.png", "type": "011", "params": {"illumination": {"color": {"brightness_factor": 1.0277001652808129, "contrast_factor": 0.9192183372201117, "saturation_factor": 0.7415641059626943}, "halo": {"num": 2, "center_a": [1087, 1265], "dia_a": 1581.006700772327, "center_b": [1087, 1265], "dia_b": 4555.629927674345}, "hole": {"center": [1309, 1268], "diameter_circle": 984, "brightness_factor": -0.2768202695901369, "rad_w": 669, "rad_h": 709, "sigma": 566.4}}, "spots": [{"radius": 31, "center": [1877, 1656], "rad_w": 13, "rad_h": 13, "sigma": 59.6}, {"radius": 87, "center": [1923, 1190], "rad_w": 33, "rad_h": 35, "sigma": 149.2}, {"radius": 96, "center": [617, 203], "rad_w": 33, "rad_h": 33, "sigma": 163.6}, {"radius": 41, "center": [914, 726], "rad_w": 17, "rad_h": 17, "sigma": 75.6}, {"radius": 27, "center": [201, 1737], "rad_w": 13, "rad_h": 11, "sigma": 53.2}, {"radius": 86, "center": [1097, 383], "rad_w": 31, "rad_h": 33, "sigma": 147.6}, {"radius": 86, "center": [405, 918], "rad_w": 29, "rad_h": 37, "sigma": 147.6}, {"radius": 103, "center": [299, 1633], "rad_w": 41, "rad_h": 35, "sigma": 174.8}]}}