{"name": "0424.png", "type": "111", "params": {"illumination": {"color": {"brightness_factor": 0.9572106795913031, "contrast_factor": 1.0598429360972659, "saturation_factor": 1.1701367922658998}, "halo": {"num": 1, "center_a": [1757, 1304], "dia_a": 2883.8974595070918, "center_b": [1757, 1304], "dia_b": 5266.343392272948}, "hole": {"center": [2167, 1576], "diameter_circle": 1238, "brightness_factor": -0.28538173763854935, "rad_w": 791, "rad_h": 769, "sigma": 631.9999999999999}}, "spots": [{"radius": 47, "center": [1659, 2193], "rad_w": 19, "rad_h": 21, "sigma": 85.19999999999999}, {"radius": 148, "center": [1713, 944], "rad_w": 59, "rad_h": 59, "sigma": 246.8}, {"radius": 126, "center": [1151, 1756], "rad_w": 51, "rad_h": 45, "sigma": 211.6}, {"radius": 123, "center": [1167, 865], "rad_w": 51, "rad_h": 49, "sigma": 206.8}, {"radius": 44, "center": [1348, 615], "rad_w": 17, "rad_h": 19, "sigma": 80.4}, {"radius": 129, "center": [161, 1032], "rad_w": 49, "rad_h": 49, "sigma": 216.4}, {"radius": 115, "center": [2356, 1001], "rad_w": 45, "rad_h": 39, "sigma": 194.0}, {"radius": 70, "center": [1931, 1336], "rad_w": 31, "rad_h": 25, "sigma": 122.0}, {"radius": 82, "center": [1428, 1470], "rad_w": 33, "rad_h": 29, "sigma": 141.2}, {"radius": 39, "center": [1802, 2813], "rad_w": 17, "rad_h": 15, "sigma": 72.4}], "blur": {"sigma": 10.979015159840092, "rad_w": 3, "rad_h": 5}}}