{"name": "0445.png", "type": "011", "params": {"illumination": {"color": {"brightness_factor": 0.9434365765986653, "contrast_factor": 1.2473149070697378, "saturation_factor": 1.3061289036846542}, "halo": {"num": 1, "center_a": [899, 914], "dia_a": 2234.849680448904, "center_b": [899, 914], "dia_b": 3405.281222716261}, "hole": {"center": [861, 936], "diameter_circle": 1448, "brightness_factor": -0.2761296695006404, "rad_w": 997, "rad_h": 803, "sigma": 796.8}}, "spots": [{"radius": 56, "center": [416, 1395], "rad_w": 25, "rad_h": 25, "sigma": 99.60000000000001}, {"radius": 72, "center": [2086, 200], "rad_w": 29, "rad_h": 31, "sigma": 125.19999999999999}, {"radius": 54, "center": [402, 1617], "rad_w": 25, "rad_h": 21, "sigma": 96.4}, {"radius": 23, "center": [220, 62], "rad_w": 11, "rad_h": 9, "sigma": 46.800000000000004}, {"radius": 33, "center": [1006, 1728], "rad_w": 15, "rad_h": 15, "sigma": 62.800000000000004}, {"radius": 95, "center": [1093, 2152], "rad_w": 33, "rad_h": 35, "sigma": 162.0}, {"radius": 48, "center": [296, 1228], "rad_w": 21, "rad_h": 21, "sigma": 86.8}]}}