{"name": "0515.png", "type": "010", "params": {"spots": [{"radius": 133, "center": [2463, 1749], "rad_w": 45, "rad_h": 55, "sigma": 222.8}, {"radius": 96, "center": [1146, 2359], "rad_w": 35, "rad_h": 33, "sigma": 163.6}, {"radius": 96, "center": [2391, 2324], "rad_w": 35, "rad_h": 37, "sigma": 163.6}, {"radius": 37, "center": [1991, 1563], "rad_w": 15, "rad_h": 13, "sigma": 69.2}, {"radius": 123, "center": [249, 805], "rad_w": 45, "rad_h": 47, "sigma": 206.8}, {"radius": 143, "center": [1923, 377], "rad_w": 59, "rad_h": 57, "sigma": 238.79999999999998}]}}