{"name": "0649.png", "type": "011", "params": {"illumination": {"color": {"brightness_factor": 0.7436310150161056, "contrast_factor": 0.6584011884818669, "saturation_factor": 1.2691619717159193}, "halo": {"num": 2, "center_a": [1219, 1535], "dia_a": 1849.8849036193092, "center_b": [1219, 1535], "dia_b": 4047.0358506905195}, "hole": {"center": [1252, 1370], "diameter_circle": 1548, "brightness_factor": -0.2874973191711658, "rad_w": 1009, "rad_h": 1023, "sigma": 817.5999999999999}}, "spots": [{"radius": 32, "center": [855, 2031], "rad_w": 13, "rad_h": 15, "sigma": 61.2}, {"radius": 48, "center": [2087, 1558], "rad_w": 21, "rad_h": 17, "sigma": 86.8}, {"radius": 35, "center": [987, 1501], "rad_w": 13, "rad_h": 15, "sigma": 66.0}, {"radius": 62, "center": [833, 1704], "rad_w": 27, "rad_h": 27, "sigma": 109.2}, {"radius": 79, "center": [2106, 1622], "rad_w": 27, "rad_h": 33, "sigma": 136.4}, {"radius": 104, "center": [1251, 2020], "rad_w": 41, "rad_h": 39, "sigma": 176.4}, {"radius": 76, "center": [1164, 502], "rad_w": 31, "rad_h": 27, "sigma": 131.6}]}}