{"name": "0650.png", "type": "010", "params": {"spots": [{"radius": 118, "center": [1682, 2716], "rad_w": 49, "rad_h": 45, "sigma": 198.79999999999998}, {"radius": 84, "center": [2363, 1453], "rad_w": 29, "rad_h": 35, "sigma": 144.4}, {"radius": 77, "center": [806, 2644], "rad_w": 29, "rad_h": 27, "sigma": 133.2}, {"radius": 119, "center": [3006, 262], "rad_w": 43, "rad_h": 41, "sigma": 200.39999999999998}, {"radius": 119, "center": [2569, 1289], "rad_w": 43, "rad_h": 47, "sigma": 200.39999999999998}, {"radius": 87, "center": [2093, 1276], "rad_w": 35, "rad_h": 33, "sigma": 149.2}]}}