{"name": "0675.png", "type": "010", "params": {"spots": [{"radius": 82, "center": [590, 1138], "rad_w": 33, "rad_h": 33, "sigma": 141.2}, {"radius": 90, "center": [782, 1628], "rad_w": 31, "rad_h": 37, "sigma": 154.0}, {"radius": 36, "center": [1965, 134], "rad_w": 17, "rad_h": 17, "sigma": 67.6}, {"radius": 76, "center": [1001, 399], "rad_w": 29, "rad_h": 27, "sigma": 131.6}, {"radius": 36, "center": [954, 1625], "rad_w": 17, "rad_h": 13, "sigma": 67.6}, {"radius": 92, "center": [1327, 1366], "rad_w": 35, "rad_h": 37, "sigma": 157.20000000000002}, {"radius": 76, "center": [1421, 1113], "rad_w": 33, "rad_h": 29, "sigma": 131.6}, {"radius": 71, "center": [1855, 1523], "rad_w": 27, "rad_h": 29, "sigma": 123.6}]}}