{"name": "0711.png", "type": "110", "params": {"spots": [{"radius": 86, "center": [2764, 2341], "rad_w": 33, "rad_h": 31, "sigma": 147.6}, {"radius": 154, "center": [2552, 589], "rad_w": 57, "rad_h": 55, "sigma": 256.4}, {"radius": 137, "center": [1902, 718], "rad_w": 57, "rad_h": 57, "sigma": 229.20000000000002}, {"radius": 123, "center": [1328, 2478], "rad_w": 43, "rad_h": 45, "sigma": 206.8}, {"radius": 102, "center": [2011, 2264], "rad_w": 39, "rad_h": 41, "sigma": 173.2}, {"radius": 130, "center": [2293, 1150], "rad_w": 47, "rad_h": 51, "sigma": 218.0}, {"radius": 127, "center": [1028, 837], "rad_w": 45, "rad_h": 53, "sigma": 213.2}, {"radius": 159, "center": [2544, 2253], "rad_w": 61, "rad_h": 65, "sigma": 264.4}, {"radius": 128, "center": [1880, 2360], "rad_w": 47, "rad_h": 45, "sigma": 214.8}, {"radius": 48, "center": [2520, 530], "rad_w": 21, "rad_h": 17, "sigma": 86.8}], "blur": {"sigma": 14.281490829355128, "rad_w": 7, "rad_h": 7}}}