{"name": "0817.png", "type": "110", "params": {"spots": [{"radius": 101, "center": [1030, 2432], "rad_w": 41, "rad_h": 37, "sigma": 171.6}, {"radius": 95, "center": [2982, 278], "rad_w": 35, "rad_h": 39, "sigma": 162.0}, {"radius": 106, "center": [3048, 1710], "rad_w": 37, "rad_h": 35, "sigma": 179.60000000000002}, {"radius": 155, "center": [2468, 2067], "rad_w": 57, "rad_h": 55, "sigma": 258.0}, {"radius": 36, "center": [1885, 515], "rad_w": 15, "rad_h": 15, "sigma": 67.6}, {"radius": 56, "center": [3022, 2147], "rad_w": 25, "rad_h": 21, "sigma": 99.60000000000001}, {"radius": 39, "center": [1670, 2362], "rad_w": 15, "rad_h": 17, "sigma": 72.4}, {"radius": 111, "center": [313, 1358], "rad_w": 39, "rad_h": 41, "sigma": 187.60000000000002}, {"radius": 37, "center": [1052, 539], "rad_w": 17, "rad_h": 15, "sigma": 69.2}], "blur": {"sigma": 12.553316158559388, "rad_w": 5, "rad_h": 7}}}