{"name": "0843.png", "type": "010", "params": {"spots": [{"radius": 64, "center": [1449, 2589], "rad_w": 25, "rad_h": 25, "sigma": 112.4}, {"radius": 68, "center": [2357, 2908], "rad_w": 29, "rad_h": 27, "sigma": 118.80000000000001}, {"radius": 42, "center": [1582, 2003], "rad_w": 19, "rad_h": 17, "sigma": 77.2}, {"radius": 135, "center": [2134, 494], "rad_w": 47, "rad_h": 55, "sigma": 226.0}, {"radius": 91, "center": [2057, 663], "rad_w": 35, "rad_h": 37, "sigma": 155.6}, {"radius": 133, "center": [2725, 984], "rad_w": 45, "rad_h": 51, "sigma": 222.8}, {"radius": 107, "center": [3052, 3030], "rad_w": 41, "rad_h": 41, "sigma": 181.20000000000002}]}}