{"name": "0883.png", "type": "011", "params": {"illumination": {"color": {"brightness_factor": 0.9927575883374378, "contrast_factor": 1.3876652043186823, "saturation_factor": 0.7355392612604232}, "halo": {"num": 1, "center_a": [1820, 1255], "dia_a": 3143.3231117961063, "center_b": [1820, 1255], "dia_b": 6458.216757511668}, "hole": {"center": [1556, 1545], "diameter_circle": 1726, "brightness_factor": -0.29633960429146855, "rad_w": 1027, "rad_h": 1147, "sigma": 917.5999999999999}}, "spots": [{"radius": 162, "center": [1685, 1357], "rad_w": 61, "rad_h": 61, "sigma": 269.20000000000005}, {"radius": 76, "center": [746, 1759], "rad_w": 27, "rad_h": 29, "sigma": 131.6}, {"radius": 62, "center": [3149, 1182], "rad_w": 25, "rad_h": 23, "sigma": 109.2}, {"radius": 66, "center": [2196, 2279], "rad_w": 23, "rad_h": 25, "sigma": 115.60000000000001}, {"radius": 122, "center": [1785, 2147], "rad_w": 51, "rad_h": 51, "sigma": 205.2}, {"radius": 140, "center": [1382, 2277], "rad_w": 59, "rad_h": 53, "sigma": 234.0}, {"radius": 58, "center": [2754, 2407], "rad_w": 25, "rad_h": 23, "sigma": 102.8}, {"radius": 82, "center": [3124, 1856], "rad_w": 33, "rad_h": 31, "sigma": 141.2}]}}